README.rst
setup.cfg
setup.py
diapason/__init__.py
diapason/core.py
diapason/dub.py
diapason.egg-info/PKG-INFO
diapason.egg-info/SOURCES.txt
diapason.egg-info/dependency_links.txt
diapason.egg-info/requires.txt
diapason.egg-info/top_level.txt