Metadata-Version: 1.1
Name: diapason
Version: 0.0.3
Summary: Python module to deal with note sounds.
Home-page: https://github.com/Soundphy/diapason
Author: Miguel Sánchez de León Peque
Author-email: peque@neosit.es
License: License :: OSI Approved :: BSD License
Keywords: diapason
Platform: UNKNOWN
Classifier: Development Status :: 1 - Planning
Classifier: Intended Audience :: Education
Classifier: Intended Audience :: End Users/Desktop
Classifier: Topic :: Education
Classifier: Topic :: Artistic Software
Classifier: Topic :: Multimedia :: Sound/Audio :: Sound Synthesis
Classifier: Topic :: Multimedia :: Sound/Audio :: Analysis
Classifier: License :: OSI Approved :: BSD License
Classifier: Programming Language :: Python :: 3
Classifier: Programming Language :: Python :: 3.5
Classifier: Programming Language :: Python :: Implementation :: CPython
